getfactormodels/__init__.py
getfactormodels/exceptions.py
getfactormodels/interface.py
getfactormodels/main.py
getfactormodels/models/__init__.py
getfactormodels/models/aqr_models.py
getfactormodels/models/aus_ccapm.py
getfactormodels/models/barillas_shanken.py
getfactormodels/models/base.py
getfactormodels/models/carhart.py
getfactormodels/models/ccapm_with_aus_WIP.py
getfactormodels/models/dhs.py
getfactormodels/models/fama_french.py
getfactormodels/models/hc_capm.py
getfactormodels/models/icr.py
getfactormodels/models/jw_ccapm.py
getfactormodels/models/liquidity.py
getfactormodels/models/mispricing.py
getfactormodels/models/q_factors.py
getfactormodels/models/stv.py
getfactormodels/registry.py
getfactormodels/utils/__init__.py
getfactormodels/utils/arrow_utils.py
getfactormodels/utils/cache.py
getfactormodels/utils/cli.py
getfactormodels/utils/date_utils.py
getfactormodels/utils/http_client.py
getfactormodels/utils/model_utils.py
getfactormodels/utils/utils.py
getfactormodels-0.0.20.dist-info/METADATA
getfactormodels-0.0.20.dist-info/WHEEL
getfactormodels-0.0.20.dist-info/entry_points.txt
getfactormodels-0.0.20.dist-info/licenses/LICENSE
getfactormodels-0.0.20.dist-info/RECORD
