Metadata-Version: 2.4
Name: getfactormodels
Version: 0.0.20
Summary: Download datasets for various multifactor asset pricing models.
License-Expression: AGPL-3.0-or-later
License-File: LICENSE
Keywords: finance,asset pricing,multifactor models,finance,price models,financial analysis
Author: S. Martin
Author-email: x512@pm.me
Requires-Python: >=3.10
Classifier: Topic :: Office/Business :: Financial
Classifier: Topic :: Office/Business :: Financial :: Investment
Classifier: Topic :: Scientific/Engineering :: Mathematics
Classifier: Intended Audience :: Financial and Insurance Industry
Classifier: Environment :: Console
Classifier: Programming Language :: Python :: 3.14
Classifier: Programming Language :: Python :: 3.13
Classifier: Programming Language :: Python :: 3.12
Classifier: Programming Language :: Python :: 3.11
Classifier: Programming Language :: Python :: 3.10
Classifier: Programming Language :: Python :: 3 :: Only
Classifier: Operating System :: OS Independent
Classifier: Development Status :: 2 - Pre-Alpha
Classifier: Natural Language :: English
Requires-Dist: certifi (>=2025.11.12,<2026.0.0)
Requires-Dist: diskcache (>=5.6.3)
Requires-Dist: httpx (>=0.28.1,<0.29.0)
Requires-Dist: platformdirs (>=4.5.1,<5.0.0)
Requires-Dist: pyarrow (>=22.0.0)
Requires-Dist: python-calamine (>=0.6.1,<0.7.0)
Requires-Dist: python-dateutil (>=2.9.0.post0,<3.0.0)
Project-URL: Download, https://pypi.org/project/getfactormodels/
Project-URL: Homepage, https://github.com/x512/getfactormodels
